{
  "mappings": {
    "_default_": {
      "dynamic": "strict",
      "_all": {
        "enabled": false
      },
      "properties": {
        "app": {
          "type": "keyword"
        },
        "modifierId": {
          "type": "long"
        },
        "mtime": {
          "type": "long"
        }
      }
    },
    "message.message": {
      "_parent": {
        "type": "message.folderRelation"
      },
      "properties": {
        "title": {
          "type": "text",
          "term_vector": "with_positions_offsets"
        },
        "data": {
          "type": "text",
          "term_vector": "with_positions_offsets"
        },
        "messageId": {
          "type": "long"
        }
      }
    },
    "message.folderRelation": {
      "properties": {
        "messageId": {
          "type": "long"
        },
        "userFolderIds": {
          "type": "long"
        },
        "userIds": {
          "type": "long"
        }
      }
    },
    "message.follow": {
      "_parent": {
        "type": "message.folderRelation"
      },
      "properties": {
        "data": {
          "type": "text",
          "term_vector": "with_positions_offsets"
        },
        "messageId": {
          "type": "long"
        },
        "followId": {
          "type": "long"
        }
      }
    },
    "message.file": {
      "_parent": {
        "type": "message.folderRelation"
      },
      "properties": {
        "name": {
          "type": "text",
          "term_vector": "with_positions_offsets"
        },
        "data": {
          "type": "text",
          "term_vector": "with_positions_offsets"
        },
        "messageId": {
          "type": "long"
        },
        "followId": {
          "type": "long"
        },
        "fileId": {
          "type": "long"
        },
        "extension": {
          "type": "keyword"
        }
      }
    },
    "bulletin.article": {
      "properties": {
        "title": {
          "type": "text",
          "term_vector": "with_positions_offsets"
        },
        "data": {
          "type": "text",
          "term_vector": "with_positions_offsets"
        },
        "articleId": {
          "type": "long"
        },
        "categoryId": {
          "type": "long"
        },
        "startTime": {
          "type": "long"
        },
        "endTime": {
          "type": "long"
        },
        "manuallyEnterSender": {
          "type": "long"
        }
      }
    },
    "bulletin.follow": {
      "properties": {
        "data": {
          "type": "text",
          "term_vector": "with_positions_offsets"
        },
        "articleId": {
          "type": "long"
        },
        "categoryId": {
          "type": "long"
        },
        "followId": {
          "type": "long"
        }
      }
    },
    "bulletin.file": {
      "properties": {
        "name": {
          "type": "text",
          "term_vector": "with_positions_offsets"
        },
        "data": {
          "type": "text",
          "term_vector": "with_positions_offsets"
        },
        "articleId": {
          "type": "long"
        },
        "categoryId": {
          "type": "long"
        },
        "followId": {
          "type": "long"
        },
        "fileId": {
          "type": "long"
        },
        "extension": {
          "type": "keyword"
        }
      }
    },
    "cabinet.file": {
      "properties": {
        "name": {
          "type": "text",
          "term_vector": "with_positions_offsets"
        },
        "title": {
          "type": "text",
          "term_vector": "with_positions_offsets"
        },
        "data": {
          "type": "text",
          "term_vector": "with_positions_offsets"
        },
        "description": {
          "type": "text",
          "term_vector": "with_positions_offsets"
        },
        "folderId": {
          "type": "long"
        },
        "fileId": {
          "type": "long"
        },
        "extension": {
          "type": "keyword"
        }
      }
    },
    "mail.message": {
      "properties": {
        "title": {
          "type": "text",
          "term_vector": "with_positions_offsets"
        },
        "data": {
          "type": "text",
          "term_vector": "with_positions_offsets"
        },
        "from": {
          "type": "text",
          "term_vector": "with_positions_offsets"
        },
        "to": {
          "type": "text",
          "term_vector": "with_positions_offsets"
        },
        "cc": {
          "type": "text",
          "term_vector": "with_positions_offsets"
        },
        "bcc": {
          "type": "text",
          "term_vector": "with_positions_offsets"
        },
        "accountId": {
          "type": "long"
        },
        "mailId": {
          "type": "long"
        },
        "folderId": {
          "type": "long"
        },
        "userId": {
          "type": "long"
        }
      }
    },
    "mail.sendFile": {
      "properties": {
        "name": {
          "type": "text",
          "term_vector": "with_positions_offsets"
        },
        "data": {
          "type": "text",
          "term_vector": "with_positions_offsets"
        },
        "from": {
          "type": "text",
          "term_vector": "with_positions_offsets"
        },
        "to": {
          "type": "text",
          "term_vector": "with_positions_offsets"
        },
        "cc": {
          "type": "text",
          "term_vector": "with_positions_offsets"
        },
        "bcc": {
          "type": "text",
          "term_vector": "with_positions_offsets"
        },
        "accountId": {
          "type": "long"
        },
        "mailId": {
          "type": "long"
        },
        "fileId": {
          "type": "long"
        },
        "folderId": {
          "type": "long"
        },
        "userId": {
          "type": "long"
        },
        "extension": {
          "type": "keyword"
        }
      }
    },
    "mail.receiveFile": {
      "properties": {
        "name": {
          "type": "text",
          "term_vector": "with_positions_offsets"
        },
        "data": {
          "type": "text",
          "term_vector": "with_positions_offsets"
        },
        "from": {
          "type": "text",
          "term_vector": "with_positions_offsets"
        },
        "to": {
          "type": "text",
          "term_vector": "with_positions_offsets"
        },
        "cc": {
          "type": "text",
          "term_vector": "with_positions_offsets"
        },
        "bcc": {
          "type": "text",
          "term_vector": "with_positions_offsets"
        },
        "accountId": {
          "type": "long"
        },
        "mailId": {
          "type": "long"
        },
        "fileId": {
          "type": "long"
        },
        "folderId": {
          "type": "long"
        },
        "userId": {
          "type": "long"
        },
        "extension": {
          "type": "keyword"
        }
      }
    },
    "space.space": {
      "properties": {
        "data": {
          "type": "text",
          "term_vector": "with_positions_offsets"
        },
        "spaceId": {
          "type": "long"
        }
      }
    },
    "space.discussion": {
      "properties": {
        "title": {
          "type": "text",
          "term_vector": "with_positions_offsets"
        },
        "data": {
          "type": "text",
          "term_vector": "with_positions_offsets"
        },
        "spaceId": {
          "type": "long"
        },
        "discussionId": {
          "type": "long"
        }
      }
    },
    "space.discussionComment": {
      "properties": {
        "data": {
          "type": "text",
          "term_vector": "with_positions_offsets"
        },
        "spaceId": {
          "type": "long"
        },
        "discussionId": {
          "type": "long"
        },
        "commentId": {
          "type": "long"
        }
      }
    },
    "space.todo": {
      "properties": {
        "title": {
          "type": "text",
          "term_vector": "with_positions_offsets"
        },
        "data": {
          "type": "text",
          "term_vector": "with_positions_offsets"
        },
        "spaceId": {
          "type": "long"
        },
        "discussionId": {
          "type": "long"
        },
        "todoId": {
          "type": "long"
        }
      }
    },
    "space.todoComment": {
      "properties": {
        "data": {
          "type": "text",
          "term_vector": "with_positions_offsets"
        },
        "spaceId": {
          "type": "long"
        },
        "discussionId": {
          "type": "long"
        },
        "todoId": {
          "type": "long"
        },
        "commentId": {
          "type": "long"
        }
      }
    },
    "space.file": {
      "properties": {
        "name": {
          "type": "text",
          "term_vector": "with_positions_offsets"
        },
        "data": {
          "type": "text",
          "term_vector": "with_positions_offsets"
        },
        "spaceId": {
          "type": "long"
        },
        "discussionId": {
          "type": "long"
        },
        "todoId": {
          "type": "long"
        },
        "commentId": {
          "type": "long"
        },
        "fileId": {
          "type": "long"
        },
        "extension": {
          "type": "keyword"
        }
      }
    }
  }
}